ezgiphy/__init__.py
ezgiphy/constants.py
ezgiphy/errors.py
ezgiphy/ezgiphy.py
ezgiphy-0.0.4.dist-info/LICENSE
ezgiphy-0.0.4.dist-info/METADATA
ezgiphy-0.0.4.dist-info/WHEEL
ezgiphy-0.0.4.dist-info/top_level.txt
ezgiphy-0.0.4.dist-info/RECORD
