Metadata-Version: 2.1
Name: ezgiphy
Version: 0.0.4
Summary: A wrapper for the giphy public API
Home-page: UNKNOWN
Author: barii.py (K.Khademul Bari)
Author-email: <barii.py@gmail.com>
License: UNKNOWN
Keywords: python,giphy,giphy api,gif
Platform: UNKNOWN
Classifier: Development Status :: 4 - Beta
Classifier: Intended Audience :: Developers
Classifier: Programming Language :: Python :: 3
Classifier: Operating System :: Unix
Classifier: Operating System :: MacOS :: MacOS X
Classifier: Operating System :: Microsoft :: Windows
